{
  "project_info": {
    "project_number": "14828229565",
    "project_id": "kios-point",
    "storage_bucket": "kios-point.firebasestorage.app"
  },
  "client": [
    {
      "client_info": {
        "mobilesdk_app_id": "1:14828229565:android:887b034687dbbcc9a1f8d4",
        "android_client_info": {
          "package_name": "io.kiospoint.user"
        }
      },
      "oauth_client": [],
      "api_key": [
        {
          "current_key": "AIzaSyAODOcloFt5BGJi2hgB65nGaSFWhWs0yQ0"
        }
      ],
      "services": {
        "appinvite_service": {
          "other_platform_oauth_client": []
        }
      }
    }
  ],
  "configuration_version": "1"
}